verdantly/__init__.py
verdantly/async_client.py
verdantly/client.py
verdantly/py.typed
verdantly-0.1.0.dist-info/licenses/LICENSE
verdantly-0.1.0.dist-info/METADATA
verdantly-0.1.0.dist-info/WHEEL
verdantly-0.1.0.dist-info/top_level.txt
verdantly-0.1.0.dist-info/RECORD
