Metadata-Version: 2.4
Name: verdantly
Version: 0.1.0
Summary: Official Verdantly client for accessing plant data
Home-page: https://github.com/verdantlyx/py-verdantly
Author: Verdantly
Author-email: hello@verdantly.io
License: MIT
Project-URL: Homepage, https://github.com/verdantlyx/py-verdantly
Project-URL: Repository, https://github.com/verdantlyx/py-verdantly
Requires-Python: >=3.7
License-File: LICENSE
Requires-Dist: requests>=2.31.0
Provides-Extra: async
Requires-Dist: httpx>=0.24.1; extra == "async"
Provides-Extra: dev
Requires-Dist: pytest; extra == "dev"
Requires-Dist: pytest-asyncio; extra == "dev"
Dynamic: license-file
